Lib/site-packages/_virtualenv.py
Lib/site-packages/typing_extensions.py
Lib/site-packages/annotated_types/__init__.py
Lib/site-packages/annotated_types/py.typed
Lib/site-packages/annotated_types/test_cases.py
Lib/site-packages/anyio/__init__.py
Lib/site-packages/anyio/from_thread.py
Lib/site-packages/anyio/lowlevel.py
Lib/site-packages/anyio/py.typed
Lib/site-packages/anyio/pytest_plugin.py
Lib/site-packages/anyio/to_interpreter.py
Lib/site-packages/anyio/to_process.py
Lib/site-packages/anyio/to_thread.py
Lib/site-packages/anyio/_backends/__init__.py
Lib/site-packages/anyio/_backends/_asyncio.py
Lib/site-packages/anyio/_backends/_trio.py
Lib/site-packages/anyio/_core/__init__.py
Lib/site-packages/anyio/_core/_asyncio_selector_thread.py
Lib/site-packages/anyio/_core/_eventloop.py
Lib/site-packages/anyio/_core/_exceptions.py
Lib/site-packages/anyio/_core/_fileio.py
Lib/site-packages/anyio/_core/_resources.py
Lib/site-packages/anyio/_core/_signals.py
Lib/site-packages/anyio/_core/_sockets.py
Lib/site-packages/anyio/_core/_streams.py
Lib/site-packages/anyio/_core/_subprocesses.py
Lib/site-packages/anyio/_core/_synchronization.py
Lib/site-packages/anyio/_core/_tasks.py
Lib/site-packages/anyio/_core/_tempfile.py
Lib/site-packages/anyio/_core/_testing.py
Lib/site-packages/anyio/_core/_typedattr.py
Lib/site-packages/anyio/abc/__init__.py
Lib/site-packages/anyio/abc/_eventloop.py
Lib/site-packages/anyio/abc/_resources.py
Lib/site-packages/anyio/abc/_sockets.py
Lib/site-packages/anyio/abc/_streams.py
Lib/site-packages/anyio/abc/_subprocesses.py
Lib/site-packages/anyio/abc/_tasks.py
Lib/site-packages/anyio/abc/_testing.py
Lib/site-packages/anyio/streams/__init__.py
Lib/site-packages/anyio/streams/buffered.py
Lib/site-packages/anyio/streams/file.py
Lib/site-packages/anyio/streams/memory.py
Lib/site-packages/anyio/streams/stapled.py
Lib/site-packages/anyio/streams/text.py
Lib/site-packages/anyio/streams/tls.py
Lib/site-packages/certifi/__init__.py
mcp_weather_example-0.7.1.dist-info/METADATA
mcp_weather_example-0.7.1.dist-info/WHEEL
mcp_weather_example-0.7.1.dist-info/entry_points.txt
mcp_weather_example-0.7.1.dist-info/top_level.txt
mcp_weather_example-0.7.1.dist-info/RECORD
