Metadata-Version: 2.4
Name: mcp_weather_example
Version: 0.7.1
Summary: Add your description here
Requires-Python: >=3.10
Requires-Dist: httpx>=0.28.1
Requires-Dist: mcp>=1.6.0
Requires-Dist: openai>=1.76.2
Requires-Dist: requests>=2.32.3
Requires-Dist: setuptools>=80.2.0
Requires-Dist: twine>=6.1.0
Requires-Dist: wheel>=0.45.1
